django_postgres_schema-0.0.1.dist-info/DESCRIPTION.rst
django_postgres_schema-0.0.1.dist-info/METADATA
django_postgres_schema-0.0.1.dist-info/RECORD
django_postgres_schema-0.0.1.dist-info/WHEEL
django_postgres_schema-0.0.1.dist-info/metadata.json
django_postgres_schema-0.0.1.dist-info/top_level.txt
postgres_schema/__init__.py
postgres_schema/apps.py
postgres_schema/models.py
postgres_schema/operations.py
postgres_schema/schema.py
postgres_schema/engine/__init__.py
postgres_schema/engine/base.py
postgres_schema/management/__init__.py
postgres_schema/management/commands/__init__.py
postgres_schema/management/commands/migrate.py
postgres_schema/migrations/0001_initial.py
postgres_schema/migrations/__init__.py
postgres_schema/sql/clone_schema.001.sql
