Metadata-Version: 2.0
Name: django-postgres-schema
Version: 0.0.1
Summary: Postgres schemas in Django.
Home-page: https://github.com/damoti/django-postgres-schema
Author: Lex Berezhny
Author-email: lex@damoti.com
License: BSD
Keywords: django,postgres,schema
Platform: UNKNOWN
Classifier: Framework :: Django
Classifier: Intended Audience :: Developers
Classifier: License :: OSI Approved :: BSD License
Classifier: Programming Language :: Python :: 3
Classifier: Operating System :: OS Independent
Classifier: Topic :: Database
Classifier: Topic :: Software Development :: Libraries :: Python Modules
